felt_upload/__init__.py
felt_upload/__main__.py
felt_upload/api.py
felt_upload/cli.py
felt_upload-0.1.3.dist-info/LICENSE
felt_upload-0.1.3.dist-info/METADATA
felt_upload-0.1.3.dist-info/WHEEL
felt_upload-0.1.3.dist-info/entry_points.txt
felt_upload-0.1.3.dist-info/RECORD
