Metadata-Version: 2.1
Name: felt-upload
Version: 0.1.3
Summary: CLI tool to upload data to Felt
Home-page: https://github.com/alekzvik/felt_upload
License: MIT
Author: Oleksii Vykaliuk
Author-email: alekzvik@gmail.com
Requires-Python: >=3.9
Classifier: License :: OSI Approved :: MIT License
Classifier: Programming Language :: Python :: 3
Classifier: Programming Language :: Python :: 3.9
Classifier: Programming Language :: Python :: 3.10
Classifier: Programming Language :: Python :: 3.11
Classifier: Programming Language :: Python :: 3.12
Classifier: Programming Language :: Python :: 3.13
Requires-Dist: requests (>=2.31.0,<3.0.0)
Requires-Dist: requests-toolbelt (>=1.0.0,<2.0.0)
Requires-Dist: typer[all] (>=0.15.1,<0.16.0)
Project-URL: Repository, https://github.com/alekzvik/felt_upload
